rest_framework_guardian/__init__.py
rest_framework_guardian/filters.py
rest_framework_guardian/serializers.py
djangorestframework_guardian2-0.7.0.dist-info/LICENSE
djangorestframework_guardian2-0.7.0.dist-info/METADATA
djangorestframework_guardian2-0.7.0.dist-info/WHEEL
djangorestframework_guardian2-0.7.0.dist-info/top_level.txt
djangorestframework_guardian2-0.7.0.dist-info/RECORD
