Metadata-Version: 2.1
Name: djangorestframework-guardian2
Version: 0.7.0
Summary: django-guardian support for Django REST Framework
Home-page: https://github.com/johnthagen/django-rest-framework-guardian2
Author: Ryan P Kilby
Author-email: kilbyr@gmail.com
License: BSD
Project-URL: Source, https://github.com/johnthagen/django-rest-framework-guardian2
Project-URL: Tracker, https://github.com/johnthagen/django-rest-framework-guardian2/issues
Classifier: Development Status :: 5 - Production/Stable
Classifier: Environment :: Web Environment
Classifier: Framework :: Django
Classifier: Framework :: Django :: 4.2
Classifier: Framework :: Django :: 5.0
Classifier: Framework :: Django :: 5.1
Classifier: Intended Audience :: Developers
Classifier: License :: OSI Approved :: BSD License
Classifier: Operating System :: OS Independent
Classifier: Programming Language :: Python
Classifier: Programming Language :: Python :: 3
Classifier: Programming Language :: Python :: 3.9
Classifier: Programming Language :: Python :: 3.10
Classifier: Programming Language :: Python :: 3.11
Classifier: Programming Language :: Python :: 3.12
Classifier: Programming Language :: Python :: 3.13
Classifier: Topic :: Internet :: WWW/HTTP
Requires-Python: >=3.9
License-File: LICENSE
Requires-Dist: django >=4.2
Requires-Dist: djangorestframework >=3.12
Requires-Dist: django-guardian >=2.4.0
